test/test_bindings.py
test/__init__.py
magna/magna.cpython-39-x86_64-linux-gnu.so
magna/config.py
magna/__main__.py
magna/__init__.py
magna/ncbi/accession.py
magna/ncbi/web.py
magna/ncbi/__init__.py
magna/rq/__init__.py
magna/cli/rq.py
magna/cli/ncbi.py
magna/cli/__init__.py
magna/diamond/__init__.py
magna/pfam/tophit.py
magna/pfam/__init__.py
magna/gtdb/ssu.py
magna/gtdb/markers.py
magna/gtdb/enums.py
magna/gtdb/metadata.py
magna/gtdb/tree.py
magna/gtdb/genome.py
magna/gtdb/msa.py
magna/gtdb/__init__.py
magna/tigrfam/tophit.py
magna/tigrfam/__init__.py
magna/util/collection.py
magna/util/pandas.py
magna/util/tree.py
magna/util/web.py
magna/util/__init__.py
magna/util/disk.py
magna/gunc/__init__.py
magna-4.1.0.data/data/LICENSE
magna-4.1.0.dist-info/LICENSE
magna-4.1.0.dist-info/top_level.txt
magna-4.1.0.dist-info/WHEEL
magna-4.1.0.dist-info/entry_points.txt
magna-4.1.0.dist-info/RECORD
magna-4.1.0.dist-info/METADATA
