Metadata-Version: 2.1
Name: magna
Version: 4.1.0
Summary: Magna is a collection of commands that I frequently use in bioinformatics and day-to-day life.
Home-page: https://github.com/aaronmussig/magna
Author: Aaron Mussig
Author-email: aaronmussig@gmail.com
License: GNU AGPLv3
Project-URL: Bug Tracker, https://github.com/aaronmussig/magna
Project-URL: Documentation, https://github.com/aaronmussig/magna
Project-URL: Source Code, https://github.com/aaronmussig/magna
Classifier: Development Status :: 4 - Beta
Classifier: Intended Audience :: Science/Research
Classifier: License :: OSI Approved :: GNU General Public License v3 (GPLv3)
Classifier: Natural Language :: English
Classifier: Operating System :: OS Independent
Classifier: Programming Language :: Python :: 3
Classifier: Programming Language :: Python :: 3.8
Classifier: Programming Language :: Python :: 3.9
Classifier: Programming Language :: Python :: 3.10
Classifier: Topic :: Scientific/Engineering :: Bio-Informatics
Classifier: Topic :: Software Development :: Libraries :: Python Modules
Requires-Python: >=3.8
License-File: LICENSE
Requires-Dist: tqdm
Requires-Dist: pandas (>=1.1.0)
Requires-Dist: pyarrow
Requires-Dist: numpy
Requires-Dist: dendropy
Requires-Dist: biopython
Requires-Dist: scipy
Requires-Dist: typer[all]
Requires-Dist: rq
Requires-Dist: redis
